{
  "products": [
    {
      "id": 2,
      "name": "Yonex Duora",
      "price": 150,
      "quantity": 30,
      "selected": true,
      "available": true
    },
    {
      "name": "Yonex Arcsaber",
      "price": 150,
      "quantity": 1,
      "selected": true,
      "available": true,
      "id": 4
    },
    {
      "name": "Yonex Armortec",
      "price": 150,
      "quantity": 1,
      "selected": true,
      "available": true,
      "id": 1
    },
    {
      "id": 5,
      "name": "Yonex Astrox",
      "price": "150",
      "quantity": "6",
      "selected": true,
      "available": true
    }
  ]
}